{
  "project_info": {
    "project_number": "551800689599",
    "firebase_url": "https://wlabs-9abe4.firebaseio.com",
    "project_id": "wlabs-9abe4",
    "storage_bucket": "wlabs-9abe4.appspot.com"
  },
  "client": [
    {
      "client_info": {
        "mobilesdk_app_id": "1:551800689599:android:e9113b31facb7c0b47c70a",
        "android_client_info": {
          "package_name": "com.wlabs.succulent_cactus"
        }
      },
      "oauth_client": [
        {
          "client_id": "551800689599-7c4rl2e2q648qkmelodqencplliu8rge.apps.googleusercontent.com",
          "client_type": 3
        }
      ],
      "api_key": [
        {
          "current_key": "AIzaSyCkt70VRao-5m11GppfMBVjpWC09Ni_qyw"
        }
      ],
      "services": {
        "appinvite_service": {
          "other_platform_oauth_client": [
            {
              "client_id": "551800689599-7c4rl2e2q648qkmelodqencplliu8rge.apps.googleusercontent.com",
              "client_type": 3
            }
          ]
        }
      }
    },
    {
      "client_info": {
        "mobilesdk_app_id": "1:551800689599:android:9337726c31c7099047c70a",
        "android_client_info": {
          "package_name": "com.wlabs.succulentcactus"
        }
      },
      "oauth_client": [
        {
          "client_id": "551800689599-7c4rl2e2q648qkmelodqencplliu8rge.apps.googleusercontent.com",
          "client_type": 3
        }
      ],
      "api_key": [
        {
          "current_key": "AIzaSyCkt70VRao-5m11GppfMBVjpWC09Ni_qyw"
        }
      ],
      "services": {
        "appinvite_service": {
          "other_platform_oauth_client": [
            {
              "client_id": "551800689599-7c4rl2e2q648qkmelodqencplliu8rge.apps.googleusercontent.com",
              "client_type": 3
            }
          ]
        }
      }
    }
  ],
  "configuration_version": "1"
}